esptest/__init__.py
esptest/__main__.py
esptest/all.py
esptest/adapter/__init__.py
esptest/adapter/dut/__init__.py
esptest/adapter/dut/create_dut.py
esptest/adapter/dut/dut_base.py
esptest/adapter/dut/esp_dut.py
esptest/adapter/dut/esp_mixin.py
esptest/adapter/dut/esp_port.py
esptest/adapter/dut/mac_mixin.py
esptest/adapter/dut/wrapper.py
esptest/adapter/port/__init__.py
esptest/adapter/port/base_port.py
esptest/adapter/port/serial_port.py
esptest/adapter/port/shell_port.py
esptest/common/__init__.py
esptest/common/compat_typing.py
esptest/common/data_monitor.py
esptest/common/decorators.py
esptest/common/encoding.py
esptest/common/generator.py
esptest/common/shell.py
esptest/common/timestamp.py
esptest/config/__init__.py
esptest/config/default_config.py
esptest/config/env_config.py
esptest/db/__init__.py
esptest/db/runners.py
esptest/devices/__init__.py
esptest/devices/attenuator.py
esptest/devices/esp_serial.py
esptest/devices/serial_dut.py
esptest/devices/serial_tools.py
esptest/devices/switch.py
esptest/env/__init__.py
esptest/env/base_env.py
esptest/env/wifi_env.py
esptest/esp_console/__init__.py
esptest/esp_console/wifi_cmd.py
esptest/interface/__init__.py
esptest/interface/dut.py
esptest/interface/port.py
esptest/iperf_utility/__init__.py
esptest/iperf_utility/iperf_results.py
esptest/iperf_utility/iperf_test.py
esptest/iperf_utility/iperf_test.test.py
esptest/iperf_utility/line_chart.py
esptest/logger/__init__.py
esptest/logger/logger.py
esptest/network/__init__.py
esptest/network/mac.py
esptest/network/netif.py
esptest/network/nic.py
esptest/scripts/downbin.py
esptest/scripts/list_ports.py
esptest/scripts/monitor.py
esptest/scripts/set_att.py
esptest/tools/copy_bin.py
esptest/tools/download_bin.py
esptest/tools/http_download.py
esptest/tools/pip_check.py
esptest/tools/uart_monitor.py
esptest/utility/gen_esp32part.py
esptest/utility/parse_bin_path.py
esp_test_utils-0.3.1.dist-info/LICENSE
esp_test_utils-0.3.1.dist-info/METADATA
esp_test_utils-0.3.1.dist-info/WHEEL
esp_test_utils-0.3.1.dist-info/entry_points.txt
esp_test_utils-0.3.1.dist-info/top_level.txt
esp_test_utils-0.3.1.dist-info/RECORD
