Metadata-Version: 2.1
Name: esp-test-utils
Version: 0.3.1
Summary: ESP Test Utils
Author-email: Chen Yudong <chenyudong@espressif.com>
License: Apache License
Project-URL: Homepage, https://github.com/ydhub/esp-test-utils
Project-URL: Repository, https://github.com/ydhub/esp-test-utils.git
Project-URL: Issues, https://github.com/ydhub/esp-test-utils/issues
Project-URL: Changelog, https://github.com/ydhub/esp-test-utils/blob/main/CHANGELOG.md
Classifier: Development Status :: 4 - Beta
Classifier: Intended Audience :: Developers
Classifier: Topic :: Software Development :: Testing
Classifier: Programming Language :: Python :: 3
Classifier: Programming Language :: Python :: 3.7
Classifier: Programming Language :: Python :: 3.8
Classifier: Programming Language :: Python :: 3.9
Classifier: Programming Language :: Python :: 3.10
Classifier: Programming Language :: Python :: 3.11
Classifier: Programming Language :: Python :: 3.12
Classifier: Programming Language :: Python :: 3.13
Requires-Python: >=3.7
License-File: LICENSE
Requires-Dist: psutil
Requires-Dist: pyserial
Requires-Dist: PyYAML
Requires-Dist: pexpect
Requires-Dist: pyusb
Requires-Dist: pyudev
Requires-Dist: esptool
Requires-Dist: packaging
Requires-Dist: rich
Requires-Dist: sqlalchemy
Requires-Dist: typing-extensions ; python_version < "3.11"
Provides-Extra: all
Requires-Dist: pyecharts ; extra == 'all'
Requires-Dist: python-gitlab ; extra == 'all'
Requires-Dist: minio ; extra == 'all'
Requires-Dist: esp-idf-monitor ; extra == 'all'
Requires-Dist: scapy ; extra == 'all'
Provides-Extra: ci-quality
Requires-Dist: pylint-gitlab ~=2.0.0 ; extra == 'ci-quality'
Requires-Dist: pylint-quotes ~=0.2.3 ; extra == 'ci-quality'
Requires-Dist: pylint ==2.17.5 ; extra == 'ci-quality'
Provides-Extra: dev
Requires-Dist: commitizen ~=3.10.1 ; extra == 'dev'
Requires-Dist: pip-tools ~=7.3 ; extra == 'dev'
Requires-Dist: pytest-cov ~=4.1.0 ; extra == 'dev'
Requires-Dist: pytest ~=7.4.0 ; extra == 'dev'
Provides-Extra: doc
Requires-Dist: sphinx ~=7.0 ; extra == 'doc'
Requires-Dist: sphinx-rtd-theme ~=2.0 ; extra == 'doc'
Provides-Extra: idfci
Requires-Dist: pyecharts ; extra == 'idfci'
Requires-Dist: python-gitlab ; extra == 'idfci'
Requires-Dist: minio ; extra == 'idfci'
Provides-Extra: mypy
Requires-Dist: types-psutil ; extra == 'mypy'
Requires-Dist: types-PyYAML ; extra == 'mypy'
Requires-Dist: types-pyserial ; extra == 'mypy'
Requires-Dist: types-pexpect ; extra == 'mypy'
Provides-Extra: test
Requires-Dist: pytest-cov ~=4.1 ; extra == 'test'
Requires-Dist: pytest ~=7.4 ; extra == 'test'
Provides-Extra: test-features
Requires-Dist: pyecharts ; extra == 'test-features'
